{
  "slug": "irene-schmidt-da-silva-alves",
  "nome": "Irene Schmidt da Silva Alves",
  "resumo_ia": "Prestou apoio técnico e colaborou no LAMPEX – Laboratório Modelo de Práticas de Extensão em 2020. Atua como extensionista no SOF – Serviço de Orientação Financeira desde 2026.",
  "anos": [
    "2020",
    "2026"
  ],
  "funcoes": [
    "APOIO TÉCNICO",
    "COLABORADOR(A)",
    "EXTENSIONISTA"
  ],
  "acoes_coordenadas": [],
  "participacoes_equipe": [
    {
      "acao_id": "3140",
      "titulo": "LAMPEX – Laboratório Modelo de Práticas de Extensão",
      "tipo": "Programa",
      "ano": "2020",
      "n": 1611,
      "funcoes": [
        "APOIO TÉCNICO",
        "COLABORADOR(A)"
      ]
    },
    {
      "acao_id": "5852",
      "titulo": "SOF – Serviço de Orientação Financeira (unidade Ifes Serra)",
      "tipo": "Projeto",
      "ano": "2026",
      "n": 316,
      "funcoes": [
        "EXTENSIONISTA"
      ]
    }
  ]
}