{
  "atividade_id": "21061",
  "numero": "091",
  "atividade": "Projeto do site SBSI 2026",
  "acao_id": "3140",
  "acao_titulo": "LAMPEX – Laboratório Modelo de Práticas de Extensão",
  "processo": "23158.001185/2020-56",
  "coordenador_acao": "Emmanuel Marques Silva",
  "publico_alvo": {
    "total": 0,
    "aprovados": 0,
    "certificados": 0,
    "situacao": {}
  },
  "equipe_execucao": [
    {
      "nome": "Anyssa Satimi Komati Andrade",
      "funcao": "EXTENSIONISTA",
      "vinculo": "Aluno"
    },
    {
      "nome": "Renan Campista",
      "funcao": "EXTENSIONISTA",
      "vinculo": "Convidado"
    }
  ]
}