{
  "atividade_id": "22292",
  "numero": "106",
  "atividade": "Desenvolvimento de Sistema de Análise de dados para cumprimento de uma proposta metodológica para avaliação do acesso à água potável e à Rede de Esgoto no Espírito Santo para meta de Desenvolvimento Sustentável 6",
  "acao_id": "3140",
  "acao_titulo": "LAMPEX – Laboratório Modelo de Práticas de Extensão",
  "processo": "23158.001185/2020-56",
  "coordenador_acao": "Emmanuel Marques Silva",
  "publico_alvo": {
    "total": 0,
    "aprovados": 0,
    "certificados": 0,
    "situacao": {}
  },
  "equipe_execucao": [
    {
      "nome": "Erick Gama Loyola",
      "funcao": "ASSESSOR(A)",
      "vinculo": "Aluno"
    }
  ]
}