{
  "atividade_id": "5300",
  "numero": "001",
  "atividade": "Ifes Portas Abertas",
  "acao_id": "1702",
  "acao_titulo": "Ifes Portas Abertas",
  "processo": "23158.000218/2018-11",
  "coordenador_acao": "Wagner Kirmse Caldas",
  "publico_alvo": {
    "total": 75,
    "aprovados": 75,
    "certificados": 75,
    "situacao": {
      "APROVADO": 75
    }
  },
  "equipe_execucao": [
    {
      "nome": "Fidelis Zanetti de Castro",
      "funcao": "COORDENADOR(A) ADJUNTO(A)",
      "vinculo": "Servidor"
    },
    {
      "nome": "Wagner Kirmse Caldas",
      "funcao": "COORDENADOR(A)",
      "vinculo": "Servidor"
    }
  ]
}